instagramfeed/__init__.py
instagramfeed/admin.py
instagramfeed/apps.py
instagramfeed/models.py
instagramfeed/migrations/__init__.py
instagramfeed/templatetags/__init__.py
instagramfeed/templatetags/instagramfeed_tags.py
mezzanine_instagram_feed-1.1.0.dist-info/LICENSE
mezzanine_instagram_feed-1.1.0.dist-info/METADATA
mezzanine_instagram_feed-1.1.0.dist-info/WHEEL
mezzanine_instagram_feed-1.1.0.dist-info/top_level.txt
mezzanine_instagram_feed-1.1.0.dist-info/RECORD
