Metadata-Version: 2.1
Name: mezzanine-instagram-feed
Version: 1.1.0
Summary: Connect Mezzaine sites to Instagram feeds
Home-page: https://github.com/unplugstudio/mezzanine-instagram-feed
Author: Unplug Studio
Author-email: hello@unplug.studio
Maintainer: Unplug Studio
Maintainer-email: hello@unplug.studio
License: MIT
Project-URL: Source, https://github.com/unplugstudio/mezzanine-instagram-feed
Project-URL: Tracker, https://github.com/unplugstudio/mezzanine-instagram-feed/issues
Keywords: django,mezzanine,instagram
Platform: any
Classifier: Development Status :: 5 - Production/Stable
Classifier: Intended Audience :: Developers
Classifier: License :: OSI Approved :: MIT License
Classifier: Operating System :: OS Independent
Classifier: Topic :: Software Development :: Libraries
Classifier: Programming Language :: Python :: 2
Classifier: Programming Language :: Python :: 2.7
Classifier: Programming Language :: Python :: 3
Classifier: Programming Language :: Python :: 3.6
Classifier: Programming Language :: Python :: 3.7
Classifier: Programming Language :: Python :: 3.8
Requires-Python: !=3.0.*,!=3.1.*,!=3.2.*,!=3.3.*,!=3.4.*,!=3.5*,>=2.7
Requires-Dist: mezzanine (>=4)
Requires-Dist: django (>=1.8)
Provides-Extra: testing
Requires-Dist: flake8 (<4,>=3) ; extra == 'testing'
Requires-Dist: pytest (<6,>=4.0.0) ; extra == 'testing'
